snakemakehelpers/__init__.py
snakemakehelpers/auto.py
snakemakehelpers/interact.py
snakemakehelpers-0.0.4.dist-info/METADATA
snakemakehelpers-0.0.4.dist-info/WHEEL
snakemakehelpers-0.0.4.dist-info/entry_points.txt
snakemakehelpers-0.0.4.dist-info/RECORD
